picasa_fetcher
