Metadata-Version: 1.0
Name: picasa-fetcher
Version: 0.2
Summary: Fetch images from Picasa
Home-page: UNKNOWN
Author: Martin Aspeli
Author-email: optilude@gmail.com
License: GPL
Keywords: jimflow picasa
Platform: UNKNOWN
